rest_framework_microservice/__init__.py
rest_framework_microservice/apps.py
rest_framework_microservice/exceptions.py
rest_framework_microservice/models.py
rest_framework_microservice/serializers.py
rest_framework_microservice/settings.py
rest_framework_microservice/urls.py
rest_framework_microservice/views.py
rest_framework_microservice/migrations/0001_initial.py
rest_framework_microservice/migrations/__init__.py
rest_framework_microservice/social_auth/__init__.py
rest_framework_microservice/social_auth/aws_cognito.py
django_rest_microservice-1.2.dist-info/METADATA
django_rest_microservice-1.2.dist-info/WHEEL
django_rest_microservice-1.2.dist-info/top_level.txt
django_rest_microservice-1.2.dist-info/RECORD
